deism/__init__.py
deism/build_count_reflections.sh
deism/core_deism.py
deism/core_deism_arg.py
deism/count_reflections.cpp
deism/count_reflections.dll
deism/count_reflections_wrapper.py
deism/data_loader.py
deism/libroom_deism.cp39-win_amd64.pyd
deism/room_check.py
deism/shared_utils.py
deism/utilities.py
deism/version.py
deism/libroom_src/common.cpp
deism/libroom_src/common.hpp
deism/libroom_src/geometry.cpp
deism/libroom_src/geometry.hpp
deism/libroom_src/libroom.cpp
deism/libroom_src/microphone.hpp
deism/libroom_src/rir_builder.cpp
deism/libroom_src/rir_builder.hpp
deism/libroom_src/room.cpp
deism/libroom_src/room.hpp
deism/libroom_src/threadpool.hpp
deism/libroom_src/wall.cpp
deism/libroom_src/wall.hpp
deism/libroom_src/ext/eigen/.hgeol
deism/libroom_src/ext/eigen/.hgignore
deism/libroom_src/ext/eigen/.hgtags
deism/libroom_src/ext/eigen/CMakeLists.txt
deism/libroom_src/ext/eigen/COPYING.BSD
deism/libroom_src/ext/eigen/COPYING.GPL
deism/libroom_src/ext/eigen/COPYING.LGPL
deism/libroom_src/ext/eigen/COPYING.MINPACK
deism/libroom_src/ext/eigen/COPYING.MPL2
deism/libroom_src/ext/eigen/COPYING.README
deism/libroom_src/ext/eigen/CTestConfig.cmake
deism/libroom_src/ext/eigen/CTestCustom.cmake.in
deism/libroom_src/ext/eigen/INSTALL
deism/libroom_src/ext/eigen/README.md
deism/libroom_src/ext/eigen/eigen3.pc.in
deism/libroom_src/ext/eigen/signature_of_eigen3_matrix_library
deism/libroom_src/ext/eigen/Eigen/CMakeLists.txt
deism/libroom_src/ext/eigen/Eigen/Cholesky
deism/libroom_src/ext/eigen/Eigen/CholmodSupport
deism/libroom_src/ext/eigen/Eigen/Core
deism/libroom_src/ext/eigen/Eigen/Dense
deism/libroom_src/ext/eigen/Eigen/Eigen
deism/libroom_src/ext/eigen/Eigen/Eigenvalues
deism/libroom_src/ext/eigen/Eigen/Geometry
deism/libroom_src/ext/eigen/Eigen/Householder
deism/libroom_src/ext/eigen/Eigen/IterativeLinearSolvers
deism/libroom_src/ext/eigen/Eigen/Jacobi
deism/libroom_src/ext/eigen/Eigen/LU
deism/libroom_src/ext/eigen/Eigen/MetisSupport
deism-2.2.1.6.dist-info/licenses/LICENSE
deism-2.2.1.6.dist-info/METADATA
deism-2.2.1.6.dist-info/WHEEL
deism-2.2.1.6.dist-info/top_level.txt
deism-2.2.1.6.dist-info/RECORD
