Metadata-Version: 2.4
Name: deism
Version: 2.2.1.6
Summary: An image source-based method used to simulate room transfer functions for arbitrary room shapes.
Home-page: https://github.com/audiolabs/DEISM
Author: Zeyu Xu, Songjiang Tan
Author-email: Zeyu Xu <zeyu.xu@audiolabs-erlangen.de>
License: 
Project-URL: Homepage, https://github.com/audiolabs/DEISM
Classifier: Programming Language :: Python :: 3
Classifier: Operating System :: OS Independent
Requires-Python: >=3.9
License-File: LICENSE
Requires-Dist: numpy==1.26
Requires-Dist: scipy
Requires-Dist: sympy
Requires-Dist: psutil
Requires-Dist: matplotlib
Requires-Dist: cython
Requires-Dist: pybind11>=2.2
Requires-Dist: ray
Requires-Dist: sound-field-analysis
Requires-Dist: gmsh
Dynamic: author
Dynamic: home-page
Dynamic: license-file
Dynamic: requires-python
